{
  "sentences": [
    {
      "index": 0,
      "parse": "(ROOT\n  (S\n    (NP\n      (NP (DT The) (NN length))\n      (PP (IN of)\n        (NP (DT a) (JJ rectangular) (NN field))))\n    (VP (VBZ is)\n      (NP (CD 24) (NNS meters)))\n    (. .)))",
      "basic-dependencies": [
        {
          "dep": "ROOT",
          "governor": 0,
          "governorGloss": "ROOT",
          "dependent": 9,
          "dependentGloss": "meters"
        },
        {
          "dep": "det",
          "governor": 2,
          "governorGloss": "length",
          "dependent": 1,
          "dependentGloss": "The"
        },
        {
          "dep": "nsubj",
          "governor": 9,
          "governorGloss": "meters",
          "dependent": 2,
          "dependentGloss": "length"
        },
        {
          "dep": "case",
          "governor": 6,
          "governorGloss": "field",
          "dependent": 3,
          "dependentGloss": "of"
        },
        {
          "dep": "det",
          "governor": 6,
          "governorGloss": "field",
          "dependent": 4,
          "dependentGloss": "a"
        },
        {
          "dep": "amod",
          "governor": 6,
          "governorGloss": "field",
          "dependent": 5,
          "dependentGloss": "rectangular"
        },
        {
          "dep": "nmod",
          "governor": 2,
          "governorGloss": "length",
          "dependent": 6,
          "dependentGloss": "field"
        },
        {
          "dep": "cop",
          "governor": 9,
          "governorGloss": "meters",
          "dependent": 7,
          "dependentGloss": "is"
        },
        {
          "dep": "nummod",
          "governor": 9,
          "governorGloss": "meters",
          "dependent": 8,
          "dependentGloss": "24"
        },
        {
          "dep": "punct",
          "governor": 9,
          "governorGloss": "meters",
          "dependent": 10,
          "dependentGloss": "."
        }
      ],
      "collapsed-dependencies": [
        {
          "dep": "ROOT",
          "governor": 0,
          "governorGloss": "ROOT",
          "dependent": 9,
          "dependentGloss": "meters"
        },
        {
          "dep": "det",
          "governor": 2,
          "governorGloss": "length",
          "dependent": 1,
          "dependentGloss": "The"
        },
        {
          "dep": "nsubj",
          "governor": 9,
          "governorGloss": "meters",
          "dependent": 2,
          "dependentGloss": "length"
        },
        {
          "dep": "case",
          "governor": 6,
          "governorGloss": "field",
          "dependent": 3,
          "dependentGloss": "of"
        },
        {
          "dep": "det",
          "governor": 6,
          "governorGloss": "field",
          "dependent": 4,
          "dependentGloss": "a"
        },
        {
          "dep": "amod",
          "governor": 6,
          "governorGloss": "field",
          "dependent": 5,
          "dependentGloss": "rectangular"
        },
        {
          "dep": "nmod:of",
          "governor": 2,
          "governorGloss": "length",
          "dependent": 6,
          "dependentGloss": "field"
        },
        {
          "dep": "cop",
          "governor": 9,
          "governorGloss": "meters",
          "dependent": 7,
          "dependentGloss": "is"
        },
        {
          "dep": "nummod",
          "governor": 9,
          "governorGloss": "meters",
          "dependent": 8,
          "dependentGloss": "24"
        },
        {
          "dep": "punct",
          "governor": 9,
          "governorGloss": "meters",
          "dependent": 10,
          "dependentGloss": "."
        }
      ],
      "collapsed-ccprocessed-dependencies": [
        {
          "dep": "ROOT",
          "governor": 0,
          "governorGloss": "ROOT",
          "dependent": 9,
          "dependentGloss": "meters"
        },
        {
          "dep": "det",
          "governor": 2,
          "governorGloss": "length",
          "dependent": 1,
          "dependentGloss": "The"
        },
        {
          "dep": "nsubj",
          "governor": 9,
          "governorGloss": "meters",
          "dependent": 2,
          "dependentGloss": "length"
        },
        {
          "dep": "case",
          "governor": 6,
          "governorGloss": "field",
          "dependent": 3,
          "dependentGloss": "of"
        },
        {
          "dep": "det",
          "governor": 6,
          "governorGloss": "field",
          "dependent": 4,
          "dependentGloss": "a"
        },
        {
          "dep": "amod",
          "governor": 6,
          "governorGloss": "field",
          "dependent": 5,
          "dependentGloss": "rectangular"
        },
        {
          "dep": "nmod:of",
          "governor": 2,
          "governorGloss": "length",
          "dependent": 6,
          "dependentGloss": "field"
        },
        {
          "dep": "cop",
          "governor": 9,
          "governorGloss": "meters",
          "dependent": 7,
          "dependentGloss": "is"
        },
        {
          "dep": "nummod",
          "governor": 9,
          "governorGloss": "meters",
          "dependent": 8,
          "dependentGloss": "24"
        },
        {
          "dep": "punct",
          "governor": 9,
          "governorGloss": "meters",
          "dependent": 10,
          "dependentGloss": "."
        }
      ],
      "tokens": [
        {
          "index": 1,
          "word": "The",
          "originalText": "The",
          "lemma": "the",
          "characterOffsetBegin": 0,
          "characterOffsetEnd": 3,
          "pos": "DT",
          "ner": "O",
          "speaker": "PER0",
          "before": "",
          "after": " "
        },
        {
          "index": 2,
          "word": "length",
          "originalText": "length",
          "lemma": "length",
          "characterOffsetBegin": 4,
          "characterOffsetEnd": 10,
          "pos": "NN",
          "ner": "O",
          "speaker": "PER0",
          "before": " ",
          "after": " "
        },
        {
          "index": 3,
          "word": "of",
          "originalText": "of",
          "lemma": "of",
          "characterOffsetBegin": 11,
          "characterOffsetEnd": 13,
          "pos": "IN",
          "ner": "O",
          "speaker": "PER0",
          "before": " ",
          "after": " "
        },
        {
          "index": 4,
          "word": "a",
          "originalText": "a",
          "lemma": "a",
          "characterOffsetBegin": 14,
          "characterOffsetEnd": 15,
          "pos": "DT",
          "ner": "O",
          "speaker": "PER0",
          "before": " ",
          "after": " "
        },
        {
          "index": 5,
          "word": "rectangular",
          "originalText": "rectangular",
          "lemma": "rectangular",
          "characterOffsetBegin": 16,
          "characterOffsetEnd": 27,
          "pos": "JJ",
          "ner": "O",
          "speaker": "PER0",
          "before": " ",
          "after": " "
        },
        {
          "index": 6,
          "word": "field",
          "originalText": "field",
          "lemma": "field",
          "characterOffsetBegin": 28,
          "characterOffsetEnd": 33,
          "pos": "NN",
          "ner": "O",
          "speaker": "PER0",
          "before": " ",
          "after": " "
        },
        {
          "index": 7,
          "word": "is",
          "originalText": "is",
          "lemma": "be",
          "characterOffsetBegin": 34,
          "characterOffsetEnd": 36,
          "pos": "VBZ",
          "ner": "O",
          "speaker": "PER0",
          "before": " ",
          "after": " "
        },
        {
          "index": 8,
          "word": "24",
          "originalText": "24",
          "lemma": "24",
          "characterOffsetBegin": 37,
          "characterOffsetEnd": 39,
          "pos": "CD",
          "ner": "NUMBER",
          "normalizedNER": "24.0",
          "speaker": "PER0",
          "before": " ",
          "after": " "
        },
        {
          "index": 9,
          "word": "meters",
          "originalText": "meters",
          "lemma": "meter",
          "characterOffsetBegin": 40,
          "characterOffsetEnd": 46,
          "pos": "NNS",
          "ner": "O",
          "speaker": "PER0",
          "before": " ",
          "after": ""
        },
        {
          "index": 10,
          "word": ".",
          "originalText": ".",
          "lemma": ".",
          "characterOffsetBegin": 46,
          "characterOffsetEnd": 47,
          "pos": ".",
          "ner": "O",
          "speaker": "PER0",
          "before": "",
          "after": " "
        }
      ]
    },
    {
      "index": 1,
      "parse": "(ROOT\n  (S\n    (NP (DT This))\n    (VP (VBZ is)\n      (ADJP\n        (ADJP\n          (NP (CD 3) (NNS meters))\n          (JJR less))\n        (PP (IN than)\n          (NP (RB twice) (DT the) (NN width)))))\n    (. .)))",
      "basic-dependencies": [
        {
          "dep": "ROOT",
          "governor": 0,
          "governorGloss": "ROOT",
          "dependent": 5,
          "dependentGloss": "less"
        },
        {
          "dep": "nsubj",
          "governor": 5,
          "governorGloss": "less",
          "dependent": 1,
          "dependentGloss": "This"
        },
        {
          "dep": "cop",
          "governor": 5,
          "governorGloss": "less",
          "dependent": 2,
          "dependentGloss": "is"
        },
        {
          "dep": "nummod",
          "governor": 4,
          "governorGloss": "meters",
          "dependent": 3,
          "dependentGloss": "3"
        },
        {
          "dep": "nmod:npmod",
          "governor": 5,
          "governorGloss": "less",
          "dependent": 4,
          "dependentGloss": "meters"
        },
        {
          "dep": "case",
          "governor": 9,
          "governorGloss": "width",
          "dependent": 6,
          "dependentGloss": "than"
        },
        {
          "dep": "advmod",
          "governor": 9,
          "governorGloss": "width",
          "dependent": 7,
          "dependentGloss": "twice"
        },
        {
          "dep": "det",
          "governor": 9,
          "governorGloss": "width",
          "dependent": 8,
          "dependentGloss": "the"
        },
        {
          "dep": "nmod",
          "governor": 5,
          "governorGloss": "less",
          "dependent": 9,
          "dependentGloss": "width"
        },
        {
          "dep": "punct",
          "governor": 5,
          "governorGloss": "less",
          "dependent": 10,
          "dependentGloss": "."
        }
      ],
      "collapsed-dependencies": [
        {
          "dep": "ROOT",
          "governor": 0,
          "governorGloss": "ROOT",
          "dependent": 5,
          "dependentGloss": "less"
        },
        {
          "dep": "nsubj",
          "governor": 5,
          "governorGloss": "less",
          "dependent": 1,
          "dependentGloss": "This"
        },
        {
          "dep": "cop",
          "governor": 5,
          "governorGloss": "less",
          "dependent": 2,
          "dependentGloss": "is"
        },
        {
          "dep": "nummod",
          "governor": 4,
          "governorGloss": "meters",
          "dependent": 3,
          "dependentGloss": "3"
        },
        {
          "dep": "nmod:npmod",
          "governor": 5,
          "governorGloss": "less",
          "dependent": 4,
          "dependentGloss": "meters"
        },
        {
          "dep": "case",
          "governor": 9,
          "governorGloss": "width",
          "dependent": 6,
          "dependentGloss": "than"
        },
        {
          "dep": "advmod",
          "governor": 9,
          "governorGloss": "width",
          "dependent": 7,
          "dependentGloss": "twice"
        },
        {
          "dep": "det",
          "governor": 9,
          "governorGloss": "width",
          "dependent": 8,
          "dependentGloss": "the"
        },
        {
          "dep": "nmod:than",
          "governor": 5,
          "governorGloss": "less",
          "dependent": 9,
          "dependentGloss": "width"
        },
        {
          "dep": "punct",
          "governor": 5,
          "governorGloss": "less",
          "dependent": 10,
          "dependentGloss": "."
        }
      ],
      "collapsed-ccprocessed-dependencies": [
        {
          "dep": "ROOT",
          "governor": 0,
          "governorGloss": "ROOT",
          "dependent": 5,
          "dependentGloss": "less"
        },
        {
          "dep": "nsubj",
          "governor": 5,
          "governorGloss": "less",
          "dependent": 1,
          "dependentGloss": "This"
        },
        {
          "dep": "cop",
          "governor": 5,
          "governorGloss": "less",
          "dependent": 2,
          "dependentGloss": "is"
        },
        {
          "dep": "nummod",
          "governor": 4,
          "governorGloss": "meters",
          "dependent": 3,
          "dependentGloss": "3"
        },
        {
          "dep": "nmod:npmod",
          "governor": 5,
          "governorGloss": "less",
          "dependent": 4,
          "dependentGloss": "meters"
        },
        {
          "dep": "case",
          "governor": 9,
          "governorGloss": "width",
          "dependent": 6,
          "dependentGloss": "than"
        },
        {
          "dep": "advmod",
          "governor": 9,
          "governorGloss": "width",
          "dependent": 7,
          "dependentGloss": "twice"
        },
        {
          "dep": "det",
          "governor": 9,
          "governorGloss": "width",
          "dependent": 8,
          "dependentGloss": "the"
        },
        {
          "dep": "nmod:than",
          "governor": 5,
          "governorGloss": "less",
          "dependent": 9,
          "dependentGloss": "width"
        },
        {
          "dep": "punct",
          "governor": 5,
          "governorGloss": "less",
          "dependent": 10,
          "dependentGloss": "."
        }
      ],
      "tokens": [
        {
          "index": 1,
          "word": "This",
          "originalText": "This",
          "lemma": "this",
          "characterOffsetBegin": 48,
          "characterOffsetEnd": 52,
          "pos": "DT",
          "ner": "O",
          "speaker": "PER0",
          "before": " ",
          "after": " "
        },
        {
          "index": 2,
          "word": "is",
          "originalText": "is",
          "lemma": "be",
          "characterOffsetBegin": 53,
          "characterOffsetEnd": 55,
          "pos": "VBZ",
          "ner": "O",
          "speaker": "PER0",
          "before": " ",
          "after": " "
        },
        {
          "index": 3,
          "word": "3",
          "originalText": "3",
          "lemma": "3",
          "characterOffsetBegin": 56,
          "characterOffsetEnd": 57,
          "pos": "CD",
          "ner": "NUMBER",
          "normalizedNER": "3.0",
          "speaker": "PER0",
          "before": " ",
          "after": " "
        },
        {
          "index": 4,
          "word": "meters",
          "originalText": "meters",
          "lemma": "meter",
          "characterOffsetBegin": 58,
          "characterOffsetEnd": 64,
          "pos": "NNS",
          "ner": "O",
          "speaker": "PER0",
          "before": " ",
          "after": " "
        },
        {
          "index": 5,
          "word": "less",
          "originalText": "less",
          "lemma": "less",
          "characterOffsetBegin": 65,
          "characterOffsetEnd": 69,
          "pos": "JJR",
          "ner": "O",
          "speaker": "PER0",
          "before": " ",
          "after": " "
        },
        {
          "index": 6,
          "word": "than",
          "originalText": "than",
          "lemma": "than",
          "characterOffsetBegin": 70,
          "characterOffsetEnd": 74,
          "pos": "IN",
          "ner": "O",
          "speaker": "PER0",
          "before": " ",
          "after": " "
        },
        {
          "index": 7,
          "word": "twice",
          "originalText": "twice",
          "lemma": "twice",
          "characterOffsetBegin": 75,
          "characterOffsetEnd": 80,
          "pos": "RB",
          "ner": "O",
          "speaker": "PER0",
          "before": " ",
          "after": " "
        },
        {
          "index": 8,
          "word": "the",
          "originalText": "the",
          "lemma": "the",
          "characterOffsetBegin": 81,
          "characterOffsetEnd": 84,
          "pos": "DT",
          "ner": "O",
          "speaker": "PER0",
          "before": " ",
          "after": " "
        },
        {
          "index": 9,
          "word": "width",
          "originalText": "width",
          "lemma": "width",
          "characterOffsetBegin": 85,
          "characterOffsetEnd": 90,
          "pos": "NN",
          "ner": "O",
          "speaker": "PER0",
          "before": " ",
          "after": ""
        },
        {
          "index": 10,
          "word": ".",
          "originalText": ".",
          "lemma": ".",
          "characterOffsetBegin": 90,
          "characterOffsetEnd": 91,
          "pos": ".",
          "ner": "O",
          "speaker": "PER0",
          "before": "",
          "after": " "
        }
      ]
    },
    {
      "index": 2,
      "parse": "(ROOT\n  (S\n    (VP (VB Find)\n      (NP (DT the) (NN width)))\n    (. .)))",
      "basic-dependencies": [
        {
          "dep": "ROOT",
          "governor": 0,
          "governorGloss": "ROOT",
          "dependent": 1,
          "dependentGloss": "Find"
        },
        {
          "dep": "det",
          "governor": 3,
          "governorGloss": "width",
          "dependent": 2,
          "dependentGloss": "the"
        },
        {
          "dep": "dobj",
          "governor": 1,
          "governorGloss": "Find",
          "dependent": 3,
          "dependentGloss": "width"
        },
        {
          "dep": "punct",
          "governor": 1,
          "governorGloss": "Find",
          "dependent": 4,
          "dependentGloss": "."
        }
      ],
      "collapsed-dependencies": [
        {
          "dep": "ROOT",
          "governor": 0,
          "governorGloss": "ROOT",
          "dependent": 1,
          "dependentGloss": "Find"
        },
        {
          "dep": "det",
          "governor": 3,
          "governorGloss": "width",
          "dependent": 2,
          "dependentGloss": "the"
        },
        {
          "dep": "dobj",
          "governor": 1,
          "governorGloss": "Find",
          "dependent": 3,
          "dependentGloss": "width"
        },
        {
          "dep": "punct",
          "governor": 1,
          "governorGloss": "Find",
          "dependent": 4,
          "dependentGloss": "."
        }
      ],
      "collapsed-ccprocessed-dependencies": [
        {
          "dep": "ROOT",
          "governor": 0,
          "governorGloss": "ROOT",
          "dependent": 1,
          "dependentGloss": "Find"
        },
        {
          "dep": "det",
          "governor": 3,
          "governorGloss": "width",
          "dependent": 2,
          "dependentGloss": "the"
        },
        {
          "dep": "dobj",
          "governor": 1,
          "governorGloss": "Find",
          "dependent": 3,
          "dependentGloss": "width"
        },
        {
          "dep": "punct",
          "governor": 1,
          "governorGloss": "Find",
          "dependent": 4,
          "dependentGloss": "."
        }
      ],
      "tokens": [
        {
          "index": 1,
          "word": "Find",
          "originalText": "Find",
          "lemma": "find",
          "characterOffsetBegin": 92,
          "characterOffsetEnd": 96,
          "pos": "VB",
          "ner": "O",
          "speaker": "PER0",
          "before": " ",
          "after": " "
        },
        {
          "index": 2,
          "word": "the",
          "originalText": "the",
          "lemma": "the",
          "characterOffsetBegin": 97,
          "characterOffsetEnd": 100,
          "pos": "DT",
          "ner": "O",
          "speaker": "PER0",
          "before": " ",
          "after": " "
        },
        {
          "index": 3,
          "word": "width",
          "originalText": "width",
          "lemma": "width",
          "characterOffsetBegin": 101,
          "characterOffsetEnd": 106,
          "pos": "NN",
          "ner": "O",
          "speaker": "PER0",
          "before": " ",
          "after": ""
        },
        {
          "index": 4,
          "word": ".",
          "originalText": ".",
          "lemma": ".",
          "characterOffsetBegin": 106,
          "characterOffsetEnd": 107,
          "pos": ".",
          "ner": "O",
          "speaker": "PER0",
          "before": "",
          "after": ""
        }
      ]
    }
  ],
  "corefs": {
    "1": [
      {
        "id": 1,
        "text": "24",
        "type": "PROPER",
        "number": "SINGULAR",
        "gender": "UNKNOWN",
        "animacy": "INANIMATE",
        "startIndex": 8,
        "endIndex": 9,
        "sentNum": 1,
        "position": [
          1,
          4
        ],
        "isRepresentativeMention": true
      }
    ],
    "2": [
      {
        "id": 2,
        "text": "The length of a rectangular field",
        "type": "NOMINAL",
        "number": "SINGULAR",
        "gender": "NEUTRAL",
        "animacy": "INANIMATE",
        "startIndex": 1,
        "endIndex": 7,
        "sentNum": 1,
        "position": [
          1,
          1
        ],
        "isRepresentativeMention": true
      }
    ],
    "3": [
      {
        "id": 3,
        "text": "a rectangular field",
        "type": "NOMINAL",
        "number": "SINGULAR",
        "gender": "UNKNOWN",
        "animacy": "INANIMATE",
        "startIndex": 4,
        "endIndex": 7,
        "sentNum": 1,
        "position": [
          1,
          2
        ],
        "isRepresentativeMention": true
      }
    ],
    "4": [
      {
        "id": 4,
        "text": "24 meters",
        "type": "NOMINAL",
        "number": "PLURAL",
        "gender": "UNKNOWN",
        "animacy": "INANIMATE",
        "startIndex": 8,
        "endIndex": 10,
        "sentNum": 1,
        "position": [
          1,
          3
        ],
        "isRepresentativeMention": true
      }
    ],
    "5": [
      {
        "id": 5,
        "text": "3",
        "type": "PROPER",
        "number": "SINGULAR",
        "gender": "UNKNOWN",
        "animacy": "INANIMATE",
        "startIndex": 3,
        "endIndex": 4,
        "sentNum": 2,
        "position": [
          2,
          3
        ],
        "isRepresentativeMention": true
      }
    ],
    "6": [
      {
        "id": 6,
        "text": "This",
        "type": "NOMINAL",
        "number": "UNKNOWN",
        "gender": "NEUTRAL",
        "animacy": "UNKNOWN",
        "startIndex": 1,
        "endIndex": 2,
        "sentNum": 2,
        "position": [
          2,
          1
        ],
        "isRepresentativeMention": true
      }
    ],
    "7": [
      {
        "id": 7,
        "text": "3 meters",
        "type": "NOMINAL",
        "number": "PLURAL",
        "gender": "UNKNOWN",
        "animacy": "INANIMATE",
        "startIndex": 3,
        "endIndex": 5,
        "sentNum": 2,
        "position": [
          2,
          2
        ],
        "isRepresentativeMention": true
      }
    ],
    "8": [
      {
        "id": 8,
        "text": "twice the width",
        "type": "NOMINAL",
        "number": "SINGULAR",
        "gender": "NEUTRAL",
        "animacy": "INANIMATE",
        "startIndex": 7,
        "endIndex": 10,
        "sentNum": 2,
        "position": [
          2,
          4
        ],
        "isRepresentativeMention": true
      },
      {
        "id": 9,
        "text": "the width",
        "type": "NOMINAL",
        "number": "SINGULAR",
        "gender": "NEUTRAL",
        "animacy": "INANIMATE",
        "startIndex": 2,
        "endIndex": 4,
        "sentNum": 3,
        "position": [
          3,
          1
        ],
        "isRepresentativeMention": false
      }
    ]
  }
}